inspr/__init__.py
inspr/client.py
inspr/models.py
inspr/rest.py
inspr/controller/__init__.py
inspr/controller/alias.py
inspr/controller/app.py
inspr/controller/channel.py
inspr/controller/client.py
inspr/controller/controller_client.py
inspr/controller/type.py
inspr-0.0.17.dist-info/LICENSE
inspr-0.0.17.dist-info/METADATA
inspr-0.0.17.dist-info/WHEEL
inspr-0.0.17.dist-info/top_level.txt
inspr-0.0.17.dist-info/RECORD
