Metadata-Version: 2.1
Name: inspr
Version: 0.0.17
Summary: This module define APIs to interact with the Inspr environment
Home-page: UNKNOWN
Author: Inspr LLC
License: UNKNOWN
Platform: UNKNOWN
Requires: requests
Requires: flask
Requires-Python: >=3.8
License-File: LICENSE
Requires-Dist: requests
Requires-Dist: flask
